tools/__init__.py
tools/myBestTools.py
myBestTools-5.4.dist-info/METADATA
myBestTools-5.4.dist-info/WHEEL
myBestTools-5.4.dist-info/top_level.txt
myBestTools-5.4.dist-info/RECORD
